impall.py
impall-1.5.3.dist-info/LICENSE
impall-1.5.3.dist-info/METADATA
impall-1.5.3.dist-info/WHEEL
impall-1.5.3.dist-info/entry_points.txt
impall-1.5.3.dist-info/RECORD
