Metadata-Version: 2.1
Name: impall
Version: 1.5.3
Summary: 🛎 Test-import all modules 🛎
Home-page: https://github.com/rec/impall
Author: Tom Ritchford
Author-email: tom@swirly.com
Requires-Python: >=3.8
Classifier: Programming Language :: Python :: 3
Classifier: Programming Language :: Python :: 3.8
Classifier: Programming Language :: Python :: 3.9
Classifier: Programming Language :: Python :: 3.10
Classifier: Programming Language :: Python :: 3.11
Classifier: Programming Language :: Python :: 3.12
Project-URL: Documentation, https://rec.github.io/impall
Project-URL: Repository, https://github.com/rec/impall
